huaweicloudsdkdas/__init__.py
huaweicloudsdkdas/v3/__init__.py
huaweicloudsdkdas/v3/das_async_client.py
huaweicloudsdkdas/v3/das_client.py
huaweicloudsdkdas/v3/model/__init__.py
huaweicloudsdkdas/v3/model/add_email_template_request.py
huaweicloudsdkdas/v3/model/add_email_template_request_body.py
huaweicloudsdkdas/v3/model/add_email_template_response.py
huaweicloudsdkdas/v3/model/add_full_sql_task_body.py
huaweicloudsdkdas/v3/model/add_full_sql_task_request.py
huaweicloudsdkdas/v3/model/add_full_sql_task_response.py
huaweicloudsdkdas/v3/model/add_instance_group_request.py
huaweicloudsdkdas/v3/model/add_instance_group_request_body.py
huaweicloudsdkdas/v3/model/add_instance_group_response.py
huaweicloudsdkdas/v3/model/add_instance_to_group_request.py
huaweicloudsdkdas/v3/model/add_instance_to_group_request_body.py
huaweicloudsdkdas/v3/model/add_instance_to_group_response.py
huaweicloudsdkdas/v3/model/advice_result.py
huaweicloudsdkdas/v3/model/api_list_connections_info_resp_das_conn_info_list.py
huaweicloudsdkdas/v3/model/api_set_metric_code_threshold_req.py
huaweicloudsdkdas/v3/model/api_version.py
huaweicloudsdkdas/v3/model/auto_increment_usage_resp_auto_increment_usage_list.py
huaweicloudsdkdas/v3/model/batch_inspection_lost_points_detail.py
huaweicloudsdkdas/v3/model/batch_inspection_report.py
huaweicloudsdkdas/v3/model/batch_send_email_request.py
huaweicloudsdkdas/v3/model/batch_send_email_request_body.py
huaweicloudsdkdas/v3/model/batch_send_email_response.py
huaweicloudsdkdas/v3/model/batch_subscribe_report_request.py
huaweicloudsdkdas/v3/model/batch_subscribe_report_request_body.py
huaweicloudsdkdas/v3/model/batch_subscribe_report_response.py
huaweicloudsdkdas/v3/model/cancel_share_connections_request.py
huaweicloudsdkdas/v3/model/cancel_share_connections_request_body.py
huaweicloudsdkdas/v3/model/cancel_share_connections_response.py
huaweicloudsdkdas/v3/model/change_charge_mode_body.py
huaweicloudsdkdas/v3/model/change_charge_mode_request.py
huaweicloudsdkdas-3.1.184.dist-info/METADATA
huaweicloudsdkdas-3.1.184.dist-info/WHEEL
huaweicloudsdkdas-3.1.184.dist-info/licenses/LICENSE
huaweicloudsdkdas-3.1.184.dist-info/RECORD
